pinsight/__init__.py
pinsight/py.typed
pinsight-0.1.0.dist-info/METADATA
pinsight-0.1.0.dist-info/WHEEL
pinsight-0.1.0.dist-info/licenses/LICENSE
pinsight-0.1.0.dist-info/RECORD
