Metadata-Version: 2.4
Name: pinsight
Version: 0.1.0
Summary: A CLI for summarizing a pins board using the Posit pins framework.
Author-email: Nathan McDougall <nathan.j.mcdougall@gmail.com>
License-File: LICENSE
Classifier: Development Status :: 1 - Planning
Classifier: Programming Language :: Python :: 3 :: Only
Classifier: Programming Language :: Python :: 3.10
Classifier: Programming Language :: Python :: 3.11
Classifier: Programming Language :: Python :: 3.12
Classifier: Programming Language :: Python :: 3.13
Requires-Python: >=3.10
